py_markdown/__init__.py
py_markdown/py_markdown.py
parce_markdown-0.0.4b0.dist-info/METADATA
parce_markdown-0.0.4b0.dist-info/WHEEL
parce_markdown-0.0.4b0.dist-info/licenses/LICENSE
parce_markdown-0.0.4b0.dist-info/RECORD
