Metadata-Version: 2.4
Name: parce-markdown
Version: 0.0.4b0
Summary: Library for parcing markdown and convert to html text or file.
Project-URL: Homepage, https://github.com/general-soldatov/py-markdown
Project-URL: Documentation, https://github.com/general-soldatov/py-markdown
Project-URL: Contacts, https://t.me/general_soldatov
Author-email: Yury Soldatov <general-soldatov@mail.ru>
License-File: LICENSE
Keywords: HTML5,code,doc-as-code,documetation,html,markdown,md
Classifier: License :: OSI Approved :: MIT License
Classifier: Operating System :: OS Independent
Classifier: Programming Language :: Python :: 3
Requires-Python: >=3.9
